odoo10_addon_partner_street_number-10.0.1.0.0-py2.7-nspkg.pth
odoo10_addon_partner_street_number-10.0.1.0.0.dist-info/top_level.txt
odoo10_addon_partner_street_number-10.0.1.0.0.dist-info/WHEEL
odoo10_addon_partner_street_number-10.0.1.0.0.dist-info/RECORD
odoo10_addon_partner_street_number-10.0.1.0.0.dist-info/metadata.json
odoo10_addon_partner_street_number-10.0.1.0.0.dist-info/DESCRIPTION.rst
odoo10_addon_partner_street_number-10.0.1.0.0.dist-info/METADATA
odoo10_addon_partner_street_number-10.0.1.0.0.dist-info/namespace_packages.txt
odoo/addons/partner_street_number/__manifest__.py
odoo/addons/partner_street_number/hooks.py
odoo/addons/partner_street_number/__init__.py
odoo/addons/partner_street_number/README.rst
odoo/addons/partner_street_number/models/res_partner.py
odoo/addons/partner_street_number/models/__init__.py
odoo/addons/partner_street_number/i18n/es.po
odoo/addons/partner_street_number/i18n/sl.po
odoo/addons/partner_street_number/i18n/nl.po
odoo/addons/partner_street_number/i18n/pt_BR.po
odoo/addons/partner_street_number/views/assets.xml
odoo/addons/partner_street_number/views/res_partner.xml
odoo/addons/partner_street_number/tests/__init__.py
odoo/addons/partner_street_number/tests/test_res_partner.py
odoo/addons/partner_street_number/static/description/icon.svg
odoo/addons/partner_street_number/static/description/icon.png
odoo/addons/partner_street_number/static/src/css/field.less
